{
  "logo": null,
  "status": "Active",
  "luxuryCar": null,
  "make_id": 25,
  "make_name": "MITSUBISHI",
  "display_order": 0,
  "make_display": "Mitsubishi",
  "is_popular": "no",
  "years": [
    {
      "year_id": 54487,
      "year": "2024",
      "models": [
        {
          "status": "Active",
          "model_id": 173,
          "make_id": 25,
          "model_name": "CEDIA",
          "model_display": "Cedia",
          "body_type": "Sedan",
          "is_popular": "no",
          "feed_img": "",
          "variants": [
            {
              "variant_id": 2166,
              "model_id": 173,
              "variant_name": "SPORTS",
              "variant_name_short": "SPORTS",
              "variant_display_name": "SPORTS",
              "transportation_category": "Category_3",
              "transmission_type": "MT",
              "fuel_type": "Petrol",
              "status": "Active",
              "tax_value": "18",
              "ex_showroom_price": 990000
            }
          ]
        }
      ]
    },
    {
      "year_id": 54486,
      "year": "2023",
      "models": [
        {
          "status": "Active",
          "model_id": 173,
          "make_id": 25,
          "model_name": "CEDIA",
          "model_display": "Cedia",
          "body_type": "Sedan",
          "is_popular": "no",
          "feed_img": "",
          "variants": [
            {
              "variant_id": 2166,
              "model_id": 173,
              "variant_name": "SPORTS",
              "variant_name_short": "SPORTS",
              "variant_display_name": "SPORTS",
              "transportation_category": "Category_3",
              "transmission_type": "MT",
              "fuel_type": "Petrol",
              "status": "Active",
              "tax_value": "18",
              "ex_showroom_price": 990000
            }
          ]
        }
      ]
    },
    {
      "year_id": 54485,
      "year": "2022",
      "models": [
        {
          "status": "Active",
          "model_id": 173,
          "make_id": 25,
          "model_name": "CEDIA",
          "model_display": "Cedia",
          "body_type": "Sedan",
          "is_popular": "no",
          "feed_img": "",
          "variants": [
            {
              "variant_id": 2166,
              "model_id": 173,
              "variant_name": "SPORTS",
              "variant_name_short": "SPORTS",
              "variant_display_name": "SPORTS",
              "transportation_category": "Category_3",
              "transmission_type": "MT",
              "fuel_type": "Petrol",
              "status": "Active",
              "tax_value": "18",
              "ex_showroom_price": 990000
            }
          ]
        }
      ]
    },
    {
      "year_id": 54484,
      "year": "2021",
      "models": [
        {
          "status": "Active",
          "model_id": 173,
          "make_id": 25,
          "model_name": "CEDIA",
          "model_display": "Cedia",
          "body_type": "Sedan",
          "is_popular": "no",
          "feed_img": "",
          "variants": [
            {
              "variant_id": 2166,
              "model_id": 173,
              "variant_name": "SPORTS",
              "variant_name_short": "SPORTS",
              "variant_display_name": "SPORTS",
              "transportation_category": "Category_3",
              "transmission_type": "MT",
              "fuel_type": "Petrol",
              "status": "Active",
              "tax_value": "18",
              "ex_showroom_price": 990000
            }
          ]
        }
      ]
    },
    {
      "year_id": 54483,
      "year": "2020",
      "models": [
        {
          "status": "Active",
          "model_id": 173,
          "make_id": 25,
          "model_name": "CEDIA",
          "model_display": "Cedia",
          "body_type": "Sedan",
          "is_popular": "no",
          "feed_img": "",
          "variants": [
            {
              "variant_id": 2166,
              "model_id": 173,
              "variant_name": "SPORTS",
              "variant_name_short": "SPORTS",
              "variant_display_name": "SPORTS",
              "transportation_category": "Category_3",
              "transmission_type": "MT",
              "fuel_type": "Petrol",
              "status": "Active",
              "tax_value": "18",
              "ex_showroom_price": 990000
            }
          ]
        }
      ]
    },
    {
      "year_id": 54482,
      "year": "2019",
      "models": [
        {
          "status": "Active",
          "model_id": 173,
          "make_id": 25,
          "model_name": "CEDIA",
          "model_display": "Cedia",
          "body_type": "Sedan",
          "is_popular": "no",
          "feed_img": "",
          "variants": [
            {
              "variant_id": 2166,
              "model_id": 173,
              "variant_name": "SPORTS",
              "variant_name_short": "SPORTS",
              "variant_display_name": "SPORTS",
              "transportation_category": "Category_3",
              "transmission_type": "MT",
              "fuel_type": "Petrol",
              "status": "Active",
              "tax_value": "18",
              "ex_showroom_price": 990000
            }
          ]
        },
        {
          "status": "Active",
          "model_id": 179,
          "make_id": 25,
          "model_name": "PAJERO SPORT",
          "model_display": "Pajero Sport",
          "body_type": "Luxury SUV",
          "is_popular": "yes",
          "feed_img": "1",
          "variants": [
            {
              "variant_id": 3277,
              "model_id": 179,
              "variant_name": "2.5 MT 4X4",
              "variant_name_short": "2.5 MT 4X4",
              "variant_display_name": "2.5 MT 4X4 [2011 - 2019]",
              "transportation_category": "Category_5",
              "transmission_type": "MT",
              "fuel_type": "Diesel",
              "status": "Active",
              "tax_value": "18",
              "ex_showroom_price": 2805000
            },
            {
              "variant_id": 5746,
              "model_id": 179,
              "variant_name": "2.5 SELECT PLUS AT",
              "variant_name_short": "2.5 SELECT PLUS AT",
              "variant_display_name": "2.5 SELECT PLUS AT",
              "transportation_category": "Category_5",
              "transmission_type": "AT",
              "fuel_type": "Diesel",
              "status": "Active",
              "tax_value": null,
              "ex_showroom_price": null
            }
          ]
        }
      ]
    },
    {
      "year_id": 54481,
      "year": "2018",
      "models": [
        {
          "status": "Active",
          "model_id": 173,
          "make_id": 25,
          "model_name": "CEDIA",
          "model_display": "Cedia",
          "body_type": "Sedan",
          "is_popular": "no",
          "feed_img": "",
          "variants": [
            {
              "variant_id": 2166,
              "model_id": 173,
              "variant_name": "SPORTS",
              "variant_name_short": "SPORTS",
              "variant_display_name": "SPORTS",
              "transportation_category": "Category_3",
              "transmission_type": "MT",
              "fuel_type": "Petrol",
              "status": "Active",
              "tax_value": "18",
              "ex_showroom_price": 990000
            }
          ]
        },
        {
          "status": "Active",
          "model_id": 175,
          "make_id": 25,
          "model_name": "LANCER EVOLUTION",
          "model_display": "Lancer Evolution",
          "body_type": "Sedan",
          "is_popular": "no",
          "feed_img": "",
          "variants": [
            {
              "variant_id": 986,
              "model_id": 175,
              "variant_name": "X",
              "variant_name_short": "X",
              "variant_display_name": "X",
              "transportation_category": "Category_4",
              "transmission_type": "MT",
              "fuel_type": "Diesel",
              "status": "Active",
              "tax_value": null,
              "ex_showroom_price": null
            }
          ]
        },
        {
          "status": "Active",
          "model_id": 176,
          "make_id": 25,
          "model_name": "MONTERO",
          "model_display": "Montero",
          "body_type": "Luxury SUV",
          "is_popular": "no",
          "feed_img": "1",
          "variants": [
            {
              "variant_id": 987,
              "model_id": 176,
              "variant_name": "DI D AT",
              "variant_name_short": "DI D AT",
              "variant_display_name": "DI D AT",
              "transportation_category": "Category_5",
              "transmission_type": "AT",
              "fuel_type": "Diesel",
              "status": "Active",
              "tax_value": "18",
              "ex_showroom_price": null
            },
            {
              "variant_id": 988,
              "model_id": 176,
              "variant_name": "DI D MT",
              "variant_name_short": "DI D MT",
              "variant_display_name": "DI D MT",
              "transportation_category": "Category_5",
              "transmission_type": "MT",
              "fuel_type": "Diesel",
              "status": "Active",
              "tax_value": "18",
              "ex_showroom_price": null
            }
          ]
        },
        {
          "status": "Active",
          "model_id": 179,
          "make_id": 25,
          "model_name": "PAJERO SPORT",
          "model_display": "Pajero Sport",
          "body_type": "Luxury SUV",
          "is_popular": "yes",
          "feed_img": "1",
          "variants": [
            {
              "variant_id": 3276,
              "model_id": 179,
              "variant_name": "2.5 AT 4X2",
              "variant_name_short": "2.5 AT 4X2",
              "variant_display_name": "2.5 AT 4X2",
              "transportation_category": "Category_5",
              "transmission_type": "AT",
              "fuel_type": "Diesel",
              "status": "Active",
              "tax_value": "18",
              "ex_showroom_price": null
            },
            {
              "variant_id": 5746,
              "model_id": 179,
              "variant_name": "2.5 SELECT PLUS AT",
              "variant_name_short": "2.5 SELECT PLUS AT",
              "variant_display_name": "2.5 SELECT PLUS AT",
              "transportation_category": "Category_5",
              "transmission_type": "AT",
              "fuel_type": "Diesel",
              "status": "Active",
              "tax_value": null,
              "ex_showroom_price": null
            },
            {
              "variant_id": 991,
              "model_id": 179,
              "variant_name": "2.5 MT",
              "variant_name_short": "2.5 MT",
              "variant_display_name": "2.5 MT",
              "transportation_category": "Category_5",
              "transmission_type": "MT",
              "fuel_type": "Diesel",
              "status": "Active",
              "tax_value": "18",
              "ex_showroom_price": null
            },
            {
              "variant_id": 3277,
              "model_id": 179,
              "variant_name": "2.5 MT 4X4",
              "variant_name_short": "2.5 MT 4X4",
              "variant_display_name": "2.5 MT 4X4 [2011 - 2019]",
              "transportation_category": "Category_5",
              "transmission_type": "MT",
              "fuel_type": "Diesel",
              "status": "Active",
              "tax_value": "18",
              "ex_showroom_price": 2805000
            }
          ]
        }
      ]
    },
    {
      "year_id": 28183,
      "year": "2017",
      "models": [
        {
          "status": "Active",
          "model_id": 173,
          "make_id": 25,
          "model_name": "CEDIA",
          "model_display": "Cedia",
          "body_type": "Sedan",
          "is_popular": "no",
          "feed_img": "",
          "variants": [
            {
              "variant_id": 2166,
              "model_id": 173,
              "variant_name": "SPORTS",
              "variant_name_short": "SPORTS",
              "variant_display_name": "SPORTS",
              "transportation_category": "Category_3",
              "transmission_type": "MT",
              "fuel_type": "Petrol",
              "status": "Active",
              "tax_value": "18",
              "ex_showroom_price": 990000
            }
          ]
        },
        {
          "status": "Active",
          "model_id": 175,
          "make_id": 25,
          "model_name": "LANCER EVOLUTION",
          "model_display": "Lancer Evolution",
          "body_type": "Sedan",
          "is_popular": "no",
          "feed_img": "",
          "variants": [
            {
              "variant_id": 986,
              "model_id": 175,
              "variant_name": "X",
              "variant_name_short": "X",
              "variant_display_name": "X",
              "transportation_category": "Category_4",
              "transmission_type": "MT",
              "fuel_type": "Diesel",
              "status": "Active",
              "tax_value": null,
              "ex_showroom_price": null
            }
          ]
        },
        {
          "status": "Active",
          "model_id": 176,
          "make_id": 25,
          "model_name": "MONTERO",
          "model_display": "Montero",
          "body_type": "Luxury SUV",
          "is_popular": "no",
          "feed_img": "1",
          "variants": [
            {
              "variant_id": 987,
              "model_id": 176,
              "variant_name": "DI D AT",
              "variant_name_short": "DI D AT",
              "variant_display_name": "DI D AT",
              "transportation_category": "Category_5",
              "transmission_type": "AT",
              "fuel_type": "Diesel",
              "status": "Active",
              "tax_value": "18",
              "ex_showroom_price": null
            },
            {
              "variant_id": 988,
              "model_id": 176,
              "variant_name": "DI D MT",
              "variant_name_short": "DI D MT",
              "variant_display_name": "DI D MT",
              "transportation_category": "Category_5",
              "transmission_type": "MT",
              "fuel_type": "Diesel",
              "status": "Active",
              "tax_value": "18",
              "ex_showroom_price": null
            }
          ]
        },
        {
          "status": "Active",
          "model_id": 179,
          "make_id": 25,
          "model_name": "PAJERO SPORT",
          "model_display": "Pajero Sport",
          "body_type": "Luxury SUV",
          "is_popular": "yes",
          "feed_img": "1",
          "variants": [
            {
              "variant_id": 3276,
              "model_id": 179,
              "variant_name": "2.5 AT 4X2",
              "variant_name_short": "2.5 AT 4X2",
              "variant_display_name": "2.5 AT 4X2",
              "transportation_category": "Category_5",
              "transmission_type": "AT",
              "fuel_type": "Diesel",
              "status": "Active",
              "tax_value": "18",
              "ex_showroom_price": null
            },
            {
              "variant_id": 991,
              "model_id": 179,
              "variant_name": "2.5 MT",
              "variant_name_short": "2.5 MT",
              "variant_display_name": "2.5 MT",
              "transportation_category": "Category_5",
              "transmission_type": "MT",
              "fuel_type": "Diesel",
              "status": "Active",
              "tax_value": "18",
              "ex_showroom_price": null
            },
            {
              "variant_id": 3277,
              "model_id": 179,
              "variant_name": "2.5 MT 4X4",
              "variant_name_short": "2.5 MT 4X4",
              "variant_display_name": "2.5 MT 4X4 [2011 - 2019]",
              "transportation_category": "Category_5",
              "transmission_type": "MT",
              "fuel_type": "Diesel",
              "status": "Active",
              "tax_value": "18",
              "ex_showroom_price": 2805000
            }
          ]
        }
      ]
    },
    {
      "year_id": 27873,
      "year": "2016",
      "models": [
        {
          "status": "Active",
          "model_id": 173,
          "make_id": 25,
          "model_name": "CEDIA",
          "model_display": "Cedia",
          "body_type": "Sedan",
          "is_popular": "no",
          "feed_img": "",
          "variants": [
            {
              "variant_id": 2162,
              "model_id": 173,
              "variant_name": "SELECT",
              "variant_name_short": "SELECT",
              "variant_display_name": "SELECT",
              "transportation_category": "Category_3",
              "transmission_type": "MT",
              "fuel_type": "Petrol",
              "status": "Active",
              "tax_value": "18",
              "ex_showroom_price": null
            },
            {
              "variant_id": 2166,
              "model_id": 173,
              "variant_name": "SPORTS",
              "variant_name_short": "SPORTS",
              "variant_display_name": "SPORTS",
              "transportation_category": "Category_3",
              "transmission_type": "MT",
              "fuel_type": "Petrol",
              "status": "Active",
              "tax_value": "18",
              "ex_showroom_price": 990000
            }
          ]
        },
        {
          "status": "Active",
          "model_id": 175,
          "make_id": 25,
          "model_name": "LANCER EVOLUTION",
          "model_display": "Lancer Evolution",
          "body_type": "Sedan",
          "is_popular": "no",
          "feed_img": "",
          "variants": [
            {
              "variant_id": 986,
              "model_id": 175,
              "variant_name": "X",
              "variant_name_short": "X",
              "variant_display_name": "X",
              "transportation_category": "Category_4",
              "transmission_type": "MT",
              "fuel_type": "Diesel",
              "status": "Active",
              "tax_value": null,
              "ex_showroom_price": null
            }
          ]
        },
        {
          "status": "Active",
          "model_id": 176,
          "make_id": 25,
          "model_name": "MONTERO",
          "model_display": "Montero",
          "body_type": "Luxury SUV",
          "is_popular": "no",
          "feed_img": "1",
          "variants": [
            {
              "variant_id": 987,
              "model_id": 176,
              "variant_name": "DI D AT",
              "variant_name_short": "DI D AT",
              "variant_display_name": "DI D AT",
              "transportation_category": "Category_5",
              "transmission_type": "AT",
              "fuel_type": "Diesel",
              "status": "Active",
              "tax_value": "18",
              "ex_showroom_price": null
            },
            {
              "variant_id": 988,
              "model_id": 176,
              "variant_name": "DI D MT",
              "variant_name_short": "DI D MT",
              "variant_display_name": "DI D MT",
              "transportation_category": "Category_5",
              "transmission_type": "MT",
              "fuel_type": "Diesel",
              "status": "Active",
              "tax_value": "18",
              "ex_showroom_price": null
            }
          ]
        },
        {
          "status": "Active",
          "model_id": 179,
          "make_id": 25,
          "model_name": "PAJERO SPORT",
          "model_display": "Pajero Sport",
          "body_type": "Luxury SUV",
          "is_popular": "yes",
          "feed_img": "1",
          "variants": [
            {
              "variant_id": 3276,
              "model_id": 179,
              "variant_name": "2.5 AT 4X2",
              "variant_name_short": "2.5 AT 4X2",
              "variant_display_name": "2.5 AT 4X2",
              "transportation_category": "Category_5",
              "transmission_type": "AT",
              "fuel_type": "Diesel",
              "status": "Active",
              "tax_value": "18",
              "ex_showroom_price": null
            },
            {
              "variant_id": 6395,
              "model_id": 179,
              "variant_name": "2.5 AT 4×2 LIMITED EDITION",
              "variant_name_short": "2.5 AT 4×2 LIMITED EDITION",
              "variant_display_name": "2.5 AT 4×2 LIMITED EDITION",
              "transportation_category": "Category_5",
              "transmission_type": "AT",
              "fuel_type": "Diesel",
              "status": "Active",
              "tax_value": null,
              "ex_showroom_price": null
            },
            {
              "variant_id": 991,
              "model_id": 179,
              "variant_name": "2.5 MT",
              "variant_name_short": "2.5 MT",
              "variant_display_name": "2.5 MT",
              "transportation_category": "Category_5",
              "transmission_type": "MT",
              "fuel_type": "Diesel",
              "status": "Active",
              "tax_value": "18",
              "ex_showroom_price": null
            },
            {
              "variant_id": 3277,
              "model_id": 179,
              "variant_name": "2.5 MT 4X4",
              "variant_name_short": "2.5 MT 4X4",
              "variant_display_name": "2.5 MT 4X4 [2011 - 2019]",
              "transportation_category": "Category_5",
              "transmission_type": "MT",
              "fuel_type": "Diesel",
              "status": "Active",
              "tax_value": "18",
              "ex_showroom_price": 2805000
            },
            {
              "variant_id": 4952,
              "model_id": 179,
              "variant_name": "2.5 MT 4×4 LIMITED EDITION",
              "variant_name_short": "2.5 MT 4×4 LIMITED EDITION",
              "variant_display_name": "2.5 MT 4×4 LIMITED EDITION",
              "transportation_category": "Category_5",
              "transmission_type": "MT",
              "fuel_type": "Diesel",
              "status": "Active",
              "tax_value": null,
              "ex_showroom_price": null
            }
          ]
        }
      ]
    },
    {
      "year_id": 984,
      "year": "2015",
      "models": [
        {
          "status": "Active",
          "model_id": 173,
          "make_id": 25,
          "model_name": "CEDIA",
          "model_display": "Cedia",
          "body_type": "Sedan",
          "is_popular": "no",
          "feed_img": "",
          "variants": [
            {
              "variant_id": 984,
              "model_id": 173,
              "variant_name": "NEW SPORTS",
              "variant_name_short": "NEW SPORTS",
              "variant_display_name": "NEW SPORTS",
              "transportation_category": "Category_3",
              "transmission_type": "MT",
              "fuel_type": "Petrol",
              "status": "Active",
              "tax_value": "18",
              "ex_showroom_price": null
            },
            {
              "variant_id": 2166,
              "model_id": 173,
              "variant_name": "SPORTS",
              "variant_name_short": "SPORTS",
              "variant_display_name": "SPORTS",
              "transportation_category": "Category_3",
              "transmission_type": "MT",
              "fuel_type": "Petrol",
              "status": "Active",
              "tax_value": "18",
              "ex_showroom_price": 990000
            }
          ]
        },
        {
          "status": "Active",
          "model_id": 174,
          "make_id": 25,
          "model_name": "LANCER",
          "model_display": "Lancer",
          "body_type": "Sedan",
          "is_popular": "yes",
          "feed_img": "",
          "variants": [
            {
              "variant_id": 985,
              "model_id": 174,
              "variant_name": "LXD 2.0",
              "variant_name_short": "LXD 2.0",
              "variant_display_name": "LXD 2.0",
              "transportation_category": "Category_4",
              "transmission_type": "MT",
              "fuel_type": "Diesel",
              "status": "Active",
              "tax_value": "18",
              "ex_showroom_price": null
            }
          ]
        },
        {
          "status": "Active",
          "model_id": 175,
          "make_id": 25,
          "model_name": "LANCER EVOLUTION",
          "model_display": "Lancer Evolution",
          "body_type": "Sedan",
          "is_popular": "no",
          "feed_img": "",
          "variants": [
            {
              "variant_id": 986,
              "model_id": 175,
              "variant_name": "X",
              "variant_name_short": "X",
              "variant_display_name": "X",
              "transportation_category": "Category_4",
              "transmission_type": "MT",
              "fuel_type": "Diesel",
              "status": "Active",
              "tax_value": null,
              "ex_showroom_price": null
            }
          ]
        },
        {
          "status": "Active",
          "model_id": 176,
          "make_id": 25,
          "model_name": "MONTERO",
          "model_display": "Montero",
          "body_type": "Luxury SUV",
          "is_popular": "no",
          "feed_img": "1",
          "variants": [
            {
              "variant_id": 987,
              "model_id": 176,
              "variant_name": "DI D AT",
              "variant_name_short": "DI D AT",
              "variant_display_name": "DI D AT",
              "transportation_category": "Category_5",
              "transmission_type": "AT",
              "fuel_type": "Diesel",
              "status": "Active",
              "tax_value": "18",
              "ex_showroom_price": null
            },
            {
              "variant_id": 988,
              "model_id": 176,
              "variant_name": "DI D MT",
              "variant_name_short": "DI D MT",
              "variant_display_name": "DI D MT",
              "transportation_category": "Category_5",
              "transmission_type": "MT",
              "fuel_type": "Diesel",
              "status": "Active",
              "tax_value": "18",
              "ex_showroom_price": null
            }
          ]
        },
        {
          "status": "Active",
          "model_id": 179,
          "make_id": 25,
          "model_name": "PAJERO SPORT",
          "model_display": "Pajero Sport",
          "body_type": "Luxury SUV",
          "is_popular": "yes",
          "feed_img": "1",
          "variants": [
            {
              "variant_id": 3276,
              "model_id": 179,
              "variant_name": "2.5 AT 4X2",
              "variant_name_short": "2.5 AT 4X2",
              "variant_display_name": "2.5 AT 4X2",
              "transportation_category": "Category_5",
              "transmission_type": "AT",
              "fuel_type": "Diesel",
              "status": "Active",
              "tax_value": "18",
              "ex_showroom_price": null
            },
            {
              "variant_id": 991,
              "model_id": 179,
              "variant_name": "2.5 MT",
              "variant_name_short": "2.5 MT",
              "variant_display_name": "2.5 MT",
              "transportation_category": "Category_5",
              "transmission_type": "MT",
              "fuel_type": "Diesel",
              "status": "Active",
              "tax_value": "18",
              "ex_showroom_price": null
            },
            {
              "variant_id": 3277,
              "model_id": 179,
              "variant_name": "2.5 MT 4X4",
              "variant_name_short": "2.5 MT 4X4",
              "variant_display_name": "2.5 MT 4X4 [2011 - 2019]",
              "transportation_category": "Category_5",
              "transmission_type": "MT",
              "fuel_type": "Diesel",
              "status": "Active",
              "tax_value": "18",
              "ex_showroom_price": 2805000
            },
            {
              "variant_id": 4952,
              "model_id": 179,
              "variant_name": "2.5 MT 4×4 LIMITED EDITION",
              "variant_name_short": "2.5 MT 4×4 LIMITED EDITION",
              "variant_display_name": "2.5 MT 4×4 LIMITED EDITION",
              "transportation_category": "Category_5",
              "transmission_type": "MT",
              "fuel_type": "Diesel",
              "status": "Active",
              "tax_value": null,
              "ex_showroom_price": null
            }
          ]
        }
      ]
    },
    {
      "year_id": 2497,
      "year": "2014",
      "models": [
        {
          "status": "Active",
          "model_id": 173,
          "make_id": 25,
          "model_name": "CEDIA",
          "model_display": "Cedia",
          "body_type": "Sedan",
          "is_popular": "no",
          "feed_img": "",
          "variants": [
            {
              "variant_id": 984,
              "model_id": 173,
              "variant_name": "NEW SPORTS",
              "variant_name_short": "NEW SPORTS",
              "variant_display_name": "NEW SPORTS",
              "transportation_category": "Category_3",
              "transmission_type": "MT",
              "fuel_type": "Petrol",
              "status": "Active",
              "tax_value": "18",
              "ex_showroom_price": null
            },
            {
              "variant_id": 2166,
              "model_id": 173,
              "variant_name": "SPORTS",
              "variant_name_short": "SPORTS",
              "variant_display_name": "SPORTS",
              "transportation_category": "Category_3",
              "transmission_type": "MT",
              "fuel_type": "Petrol",
              "status": "Active",
              "tax_value": "18",
              "ex_showroom_price": 990000
            }
          ]
        },
        {
          "status": "Active",
          "model_id": 174,
          "make_id": 25,
          "model_name": "LANCER",
          "model_display": "Lancer",
          "body_type": "Sedan",
          "is_popular": "yes",
          "feed_img": "",
          "variants": [
            {
              "variant_id": 985,
              "model_id": 174,
              "variant_name": "LXD 2.0",
              "variant_name_short": "LXD 2.0",
              "variant_display_name": "LXD 2.0",
              "transportation_category": "Category_4",
              "transmission_type": "MT",
              "fuel_type": "Diesel",
              "status": "Active",
              "tax_value": "18",
              "ex_showroom_price": null
            }
          ]
        },
        {
          "status": "Active",
          "model_id": 175,
          "make_id": 25,
          "model_name": "LANCER EVOLUTION",
          "model_display": "Lancer Evolution",
          "body_type": "Sedan",
          "is_popular": "no",
          "feed_img": "",
          "variants": [
            {
              "variant_id": 986,
              "model_id": 175,
              "variant_name": "X",
              "variant_name_short": "X",
              "variant_display_name": "X",
              "transportation_category": "Category_4",
              "transmission_type": "MT",
              "fuel_type": "Diesel",
              "status": "Active",
              "tax_value": null,
              "ex_showroom_price": null
            }
          ]
        },
        {
          "status": "Active",
          "model_id": 176,
          "make_id": 25,
          "model_name": "MONTERO",
          "model_display": "Montero",
          "body_type": "Luxury SUV",
          "is_popular": "no",
          "feed_img": "1",
          "variants": [
            {
              "variant_id": 987,
              "model_id": 176,
              "variant_name": "DI D AT",
              "variant_name_short": "DI D AT",
              "variant_display_name": "DI D AT",
              "transportation_category": "Category_5",
              "transmission_type": "AT",
              "fuel_type": "Diesel",
              "status": "Active",
              "tax_value": "18",
              "ex_showroom_price": null
            },
            {
              "variant_id": 988,
              "model_id": 176,
              "variant_name": "DI D MT",
              "variant_name_short": "DI D MT",
              "variant_display_name": "DI D MT",
              "transportation_category": "Category_5",
              "transmission_type": "MT",
              "fuel_type": "Diesel",
              "status": "Active",
              "tax_value": "18",
              "ex_showroom_price": null
            }
          ]
        },
        {
          "status": "Active",
          "model_id": 179,
          "make_id": 25,
          "model_name": "PAJERO SPORT",
          "model_display": "Pajero Sport",
          "body_type": "Luxury SUV",
          "is_popular": "yes",
          "feed_img": "1",
          "variants": [
            {
              "variant_id": 3276,
              "model_id": 179,
              "variant_name": "2.5 AT 4X2",
              "variant_name_short": "2.5 AT 4X2",
              "variant_display_name": "2.5 AT 4X2",
              "transportation_category": "Category_5",
              "transmission_type": "AT",
              "fuel_type": "Diesel",
              "status": "Active",
              "tax_value": "18",
              "ex_showroom_price": null
            },
            {
              "variant_id": 991,
              "model_id": 179,
              "variant_name": "2.5 MT",
              "variant_name_short": "2.5 MT",
              "variant_display_name": "2.5 MT",
              "transportation_category": "Category_5",
              "transmission_type": "MT",
              "fuel_type": "Diesel",
              "status": "Active",
              "tax_value": "18",
              "ex_showroom_price": null
            },
            {
              "variant_id": 3277,
              "model_id": 179,
              "variant_name": "2.5 MT 4X4",
              "variant_name_short": "2.5 MT 4X4",
              "variant_display_name": "2.5 MT 4X4 [2011 - 2019]",
              "transportation_category": "Category_5",
              "transmission_type": "MT",
              "fuel_type": "Diesel",
              "status": "Active",
              "tax_value": "18",
              "ex_showroom_price": 2805000
            },
            {
              "variant_id": 4952,
              "model_id": 179,
              "variant_name": "2.5 MT 4×4 LIMITED EDITION",
              "variant_name_short": "2.5 MT 4×4 LIMITED EDITION",
              "variant_display_name": "2.5 MT 4×4 LIMITED EDITION",
              "transportation_category": "Category_5",
              "transmission_type": "MT",
              "fuel_type": "Diesel",
              "status": "Active",
              "tax_value": null,
              "ex_showroom_price": null
            },
            {
              "variant_id": 5040,
              "model_id": 179,
              "variant_name": "2.5 MT ANNIVERSARY EDITION",
              "variant_name_short": "2.5 MT ANNIVERSARY EDITION",
              "variant_display_name": "2.5 MT ANNIVERSARY EDITION",
              "transportation_category": "Category_5",
              "transmission_type": "MT",
              "fuel_type": "Diesel",
              "status": "Active",
              "tax_value": null,
              "ex_showroom_price": null
            },
            {
              "variant_id": 5974,
              "model_id": 179,
              "variant_name": "Anniversary Edition 4x4",
              "variant_name_short": "Anniversary Edition 4x4",
              "variant_display_name": "Anniversary Edition 4x4",
              "transportation_category": "Category_5",
              "transmission_type": "MT",
              "fuel_type": "Diesel",
              "status": "Active",
              "tax_value": null,
              "ex_showroom_price": null
            }
          ]
        }
      ]
    },
    {
      "year_id": 3823,
      "year": "2013",
      "models": [
        {
          "status": "Active",
          "model_id": 173,
          "make_id": 25,
          "model_name": "CEDIA",
          "model_display": "Cedia",
          "body_type": "Sedan",
          "is_popular": "no",
          "feed_img": "",
          "variants": [
            {
              "variant_id": 984,
              "model_id": 173,
              "variant_name": "NEW SPORTS",
              "variant_name_short": "NEW SPORTS",
              "variant_display_name": "NEW SPORTS",
              "transportation_category": "Category_3",
              "transmission_type": "MT",
              "fuel_type": "Petrol",
              "status": "Active",
              "tax_value": "18",
              "ex_showroom_price": null
            },
            {
              "variant_id": 2166,
              "model_id": 173,
              "variant_name": "SPORTS",
              "variant_name_short": "SPORTS",
              "variant_display_name": "SPORTS",
              "transportation_category": "Category_3",
              "transmission_type": "MT",
              "fuel_type": "Petrol",
              "status": "Active",
              "tax_value": "18",
              "ex_showroom_price": 990000
            }
          ]
        },
        {
          "status": "Active",
          "model_id": 174,
          "make_id": 25,
          "model_name": "LANCER",
          "model_display": "Lancer",
          "body_type": "Sedan",
          "is_popular": "yes",
          "feed_img": "",
          "variants": [
            {
              "variant_id": 985,
              "model_id": 174,
              "variant_name": "LXD 2.0",
              "variant_name_short": "LXD 2.0",
              "variant_display_name": "LXD 2.0",
              "transportation_category": "Category_4",
              "transmission_type": "MT",
              "fuel_type": "Diesel",
              "status": "Active",
              "tax_value": "18",
              "ex_showroom_price": null
            }
          ]
        },
        {
          "status": "Active",
          "model_id": 175,
          "make_id": 25,
          "model_name": "LANCER EVOLUTION",
          "model_display": "Lancer Evolution",
          "body_type": "Sedan",
          "is_popular": "no",
          "feed_img": "",
          "variants": [
            {
              "variant_id": 986,
              "model_id": 175,
              "variant_name": "X",
              "variant_name_short": "X",
              "variant_display_name": "X",
              "transportation_category": "Category_4",
              "transmission_type": "MT",
              "fuel_type": "Diesel",
              "status": "Active",
              "tax_value": null,
              "ex_showroom_price": null
            }
          ]
        },
        {
          "status": "Active",
          "model_id": 176,
          "make_id": 25,
          "model_name": "MONTERO",
          "model_display": "Montero",
          "body_type": "Luxury SUV",
          "is_popular": "no",
          "feed_img": "1",
          "variants": [
            {
              "variant_id": 987,
              "model_id": 176,
              "variant_name": "DI D AT",
              "variant_name_short": "DI D AT",
              "variant_display_name": "DI D AT",
              "transportation_category": "Category_5",
              "transmission_type": "AT",
              "fuel_type": "Diesel",
              "status": "Active",
              "tax_value": "18",
              "ex_showroom_price": null
            },
            {
              "variant_id": 988,
              "model_id": 176,
              "variant_name": "DI D MT",
              "variant_name_short": "DI D MT",
              "variant_display_name": "DI D MT",
              "transportation_category": "Category_5",
              "transmission_type": "MT",
              "fuel_type": "Diesel",
              "status": "Active",
              "tax_value": "18",
              "ex_showroom_price": null
            }
          ]
        },
        {
          "status": "Active",
          "model_id": 177,
          "make_id": 25,
          "model_name": "OUTLANDER",
          "model_display": "Outlander",
          "body_type": "Luxury SUV",
          "is_popular": "yes",
          "feed_img": "1",
          "variants": [
            {
              "variant_id": 989,
              "model_id": 177,
              "variant_name": "2.4 MIVEC",
              "variant_name_short": "2.4 MIVEC",
              "variant_display_name": "2.4 MIVEC [2008 - 2013]",
              "transportation_category": "Category_5",
              "transmission_type": "MT",
              "fuel_type": "Petrol",
              "status": "Active",
              "tax_value": "18",
              "ex_showroom_price": 2048000
            }
          ]
        },
        {
          "status": "Active",
          "model_id": 179,
          "make_id": 25,
          "model_name": "PAJERO SPORT",
          "model_display": "Pajero Sport",
          "body_type": "Luxury SUV",
          "is_popular": "yes",
          "feed_img": "1",
          "variants": [
            {
              "variant_id": 991,
              "model_id": 179,
              "variant_name": "2.5 MT",
              "variant_name_short": "2.5 MT",
              "variant_display_name": "2.5 MT",
              "transportation_category": "Category_5",
              "transmission_type": "MT",
              "fuel_type": "Diesel",
              "status": "Active",
              "tax_value": "18",
              "ex_showroom_price": null
            },
            {
              "variant_id": 3277,
              "model_id": 179,
              "variant_name": "2.5 MT 4X4",
              "variant_name_short": "2.5 MT 4X4",
              "variant_display_name": "2.5 MT 4X4 [2011 - 2019]",
              "transportation_category": "Category_5",
              "transmission_type": "MT",
              "fuel_type": "Diesel",
              "status": "Active",
              "tax_value": "18",
              "ex_showroom_price": 2805000
            },
            {
              "variant_id": 5040,
              "model_id": 179,
              "variant_name": "2.5 MT ANNIVERSARY EDITION",
              "variant_name_short": "2.5 MT ANNIVERSARY EDITION",
              "variant_display_name": "2.5 MT ANNIVERSARY EDITION",
              "transportation_category": "Category_5",
              "transmission_type": "MT",
              "fuel_type": "Diesel",
              "status": "Active",
              "tax_value": null,
              "ex_showroom_price": null
            }
          ]
        }
      ]
    },
    {
      "year_id": 4936,
      "year": "2012",
      "models": [
        {
          "status": "Active",
          "model_id": 173,
          "make_id": 25,
          "model_name": "CEDIA",
          "model_display": "Cedia",
          "body_type": "Sedan",
          "is_popular": "no",
          "feed_img": "",
          "variants": [
            {
              "variant_id": 984,
              "model_id": 173,
              "variant_name": "NEW SPORTS",
              "variant_name_short": "NEW SPORTS",
              "variant_display_name": "NEW SPORTS",
              "transportation_category": "Category_3",
              "transmission_type": "MT",
              "fuel_type": "Petrol",
              "status": "Active",
              "tax_value": "18",
              "ex_showroom_price": null
            },
            {
              "variant_id": 2162,
              "model_id": 173,
              "variant_name": "SELECT",
              "variant_name_short": "SELECT",
              "variant_display_name": "SELECT",
              "transportation_category": "Category_3",
              "transmission_type": "MT",
              "fuel_type": "Petrol",
              "status": "Active",
              "tax_value": "18",
              "ex_showroom_price": null
            },
            {
              "variant_id": 2166,
              "model_id": 173,
              "variant_name": "SPORTS",
              "variant_name_short": "SPORTS",
              "variant_display_name": "SPORTS",
              "transportation_category": "Category_3",
              "transmission_type": "MT",
              "fuel_type": "Petrol",
              "status": "Active",
              "tax_value": "18",
              "ex_showroom_price": 990000
            }
          ]
        },
        {
          "status": "Active",
          "model_id": 174,
          "make_id": 25,
          "model_name": "LANCER",
          "model_display": "Lancer",
          "body_type": "Sedan",
          "is_popular": "yes",
          "feed_img": "",
          "variants": [
            {
              "variant_id": 985,
              "model_id": 174,
              "variant_name": "LXD 2.0",
              "variant_name_short": "LXD 2.0",
              "variant_display_name": "LXD 2.0",
              "transportation_category": "Category_4",
              "transmission_type": "MT",
              "fuel_type": "Diesel",
              "status": "Active",
              "tax_value": "18",
              "ex_showroom_price": null
            }
          ]
        },
        {
          "status": "Active",
          "model_id": 175,
          "make_id": 25,
          "model_name": "LANCER EVOLUTION",
          "model_display": "Lancer Evolution",
          "body_type": "Sedan",
          "is_popular": "no",
          "feed_img": "",
          "variants": [
            {
              "variant_id": 986,
              "model_id": 175,
              "variant_name": "X",
              "variant_name_short": "X",
              "variant_display_name": "X",
              "transportation_category": "Category_4",
              "transmission_type": "MT",
              "fuel_type": "Diesel",
              "status": "Active",
              "tax_value": null,
              "ex_showroom_price": null
            }
          ]
        },
        {
          "status": "Active",
          "model_id": 176,
          "make_id": 25,
          "model_name": "MONTERO",
          "model_display": "Montero",
          "body_type": "Luxury SUV",
          "is_popular": "no",
          "feed_img": "1",
          "variants": [
            {
              "variant_id": 987,
              "model_id": 176,
              "variant_name": "DI D AT",
              "variant_name_short": "DI D AT",
              "variant_display_name": "DI D AT",
              "transportation_category": "Category_5",
              "transmission_type": "AT",
              "fuel_type": "Diesel",
              "status": "Active",
              "tax_value": "18",
              "ex_showroom_price": null
            },
            {
              "variant_id": 988,
              "model_id": 176,
              "variant_name": "DI D MT",
              "variant_name_short": "DI D MT",
              "variant_display_name": "DI D MT",
              "transportation_category": "Category_5",
              "transmission_type": "MT",
              "fuel_type": "Diesel",
              "status": "Active",
              "tax_value": "18",
              "ex_showroom_price": null
            }
          ]
        },
        {
          "status": "Active",
          "model_id": 177,
          "make_id": 25,
          "model_name": "OUTLANDER",
          "model_display": "Outlander",
          "body_type": "Luxury SUV",
          "is_popular": "yes",
          "feed_img": "1",
          "variants": [
            {
              "variant_id": 989,
              "model_id": 177,
              "variant_name": "2.4 MIVEC",
              "variant_name_short": "2.4 MIVEC",
              "variant_display_name": "2.4 MIVEC [2008 - 2013]",
              "transportation_category": "Category_5",
              "transmission_type": "MT",
              "fuel_type": "Petrol",
              "status": "Active",
              "tax_value": "18",
              "ex_showroom_price": 2048000
            }
          ]
        },
        {
          "status": "Active",
          "model_id": 179,
          "make_id": 25,
          "model_name": "PAJERO SPORT",
          "model_display": "Pajero Sport",
          "body_type": "Luxury SUV",
          "is_popular": "yes",
          "feed_img": "1",
          "variants": [
            {
              "variant_id": 991,
              "model_id": 179,
              "variant_name": "2.5 MT",
              "variant_name_short": "2.5 MT",
              "variant_display_name": "2.5 MT",
              "transportation_category": "Category_5",
              "transmission_type": "MT",
              "fuel_type": "Diesel",
              "status": "Active",
              "tax_value": "18",
              "ex_showroom_price": null
            },
            {
              "variant_id": 3277,
              "model_id": 179,
              "variant_name": "2.5 MT 4X4",
              "variant_name_short": "2.5 MT 4X4",
              "variant_display_name": "2.5 MT 4X4 [2011 - 2019]",
              "transportation_category": "Category_5",
              "transmission_type": "MT",
              "fuel_type": "Diesel",
              "status": "Active",
              "tax_value": "18",
              "ex_showroom_price": 2805000
            }
          ]
        }
      ]
    },
    {
      "year_id": 6012,
      "year": "2011",
      "models": [
        {
          "status": "Active",
          "model_id": 173,
          "make_id": 25,
          "model_name": "CEDIA",
          "model_display": "Cedia",
          "body_type": "Sedan",
          "is_popular": "no",
          "feed_img": "",
          "variants": [
            {
              "variant_id": 984,
              "model_id": 173,
              "variant_name": "NEW SPORTS",
              "variant_name_short": "NEW SPORTS",
              "variant_display_name": "NEW SPORTS",
              "transportation_category": "Category_3",
              "transmission_type": "MT",
              "fuel_type": "Petrol",
              "status": "Active",
              "tax_value": "18",
              "ex_showroom_price": null
            },
            {
              "variant_id": 2166,
              "model_id": 173,
              "variant_name": "SPORTS",
              "variant_name_short": "SPORTS",
              "variant_display_name": "SPORTS",
              "transportation_category": "Category_3",
              "transmission_type": "MT",
              "fuel_type": "Petrol",
              "status": "Active",
              "tax_value": "18",
              "ex_showroom_price": 990000
            }
          ]
        },
        {
          "status": "Active",
          "model_id": 174,
          "make_id": 25,
          "model_name": "LANCER",
          "model_display": "Lancer",
          "body_type": "Sedan",
          "is_popular": "yes",
          "feed_img": "",
          "variants": [
            {
              "variant_id": 985,
              "model_id": 174,
              "variant_name": "LXD 2.0",
              "variant_name_short": "LXD 2.0",
              "variant_display_name": "LXD 2.0",
              "transportation_category": "Category_4",
              "transmission_type": "MT",
              "fuel_type": "Diesel",
              "status": "Active",
              "tax_value": "18",
              "ex_showroom_price": null
            }
          ]
        },
        {
          "status": "Active",
          "model_id": 175,
          "make_id": 25,
          "model_name": "LANCER EVOLUTION",
          "model_display": "Lancer Evolution",
          "body_type": "Sedan",
          "is_popular": "no",
          "feed_img": "",
          "variants": [
            {
              "variant_id": 986,
              "model_id": 175,
              "variant_name": "X",
              "variant_name_short": "X",
              "variant_display_name": "X",
              "transportation_category": "Category_4",
              "transmission_type": "MT",
              "fuel_type": "Diesel",
              "status": "Active",
              "tax_value": null,
              "ex_showroom_price": null
            }
          ]
        },
        {
          "status": "Active",
          "model_id": 176,
          "make_id": 25,
          "model_name": "MONTERO",
          "model_display": "Montero",
          "body_type": "Luxury SUV",
          "is_popular": "no",
          "feed_img": "1",
          "variants": [
            {
              "variant_id": 3300,
              "model_id": 176,
              "variant_name": "3.2 GLS 4x4 AT",
              "variant_name_short": "3.2 GLS 4x4 AT",
              "variant_display_name": "3.2 GLS 4x4 AT",
              "transportation_category": "Category_5",
              "transmission_type": "AT",
              "fuel_type": "Diesel",
              "status": "Active",
              "tax_value": null,
              "ex_showroom_price": null
            },
            {
              "variant_id": 987,
              "model_id": 176,
              "variant_name": "DI D AT",
              "variant_name_short": "DI D AT",
              "variant_display_name": "DI D AT",
              "transportation_category": "Category_5",
              "transmission_type": "AT",
              "fuel_type": "Diesel",
              "status": "Active",
              "tax_value": "18",
              "ex_showroom_price": null
            },
            {
              "variant_id": 988,
              "model_id": 176,
              "variant_name": "DI D MT",
              "variant_name_short": "DI D MT",
              "variant_display_name": "DI D MT",
              "transportation_category": "Category_5",
              "transmission_type": "MT",
              "fuel_type": "Diesel",
              "status": "Active",
              "tax_value": "18",
              "ex_showroom_price": null
            }
          ]
        },
        {
          "status": "Active",
          "model_id": 177,
          "make_id": 25,
          "model_name": "OUTLANDER",
          "model_display": "Outlander",
          "body_type": "Luxury SUV",
          "is_popular": "yes",
          "feed_img": "1",
          "variants": [
            {
              "variant_id": 989,
              "model_id": 177,
              "variant_name": "2.4 MIVEC",
              "variant_name_short": "2.4 MIVEC",
              "variant_display_name": "2.4 MIVEC [2008 - 2013]",
              "transportation_category": "Category_5",
              "transmission_type": "MT",
              "fuel_type": "Petrol",
              "status": "Active",
              "tax_value": "18",
              "ex_showroom_price": 2048000
            }
          ]
        },
        {
          "status": "Active",
          "model_id": 179,
          "make_id": 25,
          "model_name": "PAJERO SPORT",
          "model_display": "Pajero Sport",
          "body_type": "Luxury SUV",
          "is_popular": "yes",
          "feed_img": "1",
          "variants": [
            {
              "variant_id": 991,
              "model_id": 179,
              "variant_name": "2.5 MT",
              "variant_name_short": "2.5 MT",
              "variant_display_name": "2.5 MT",
              "transportation_category": "Category_5",
              "transmission_type": "MT",
              "fuel_type": "Diesel",
              "status": "Active",
              "tax_value": "18",
              "ex_showroom_price": null
            },
            {
              "variant_id": 3277,
              "model_id": 179,
              "variant_name": "2.5 MT 4X4",
              "variant_name_short": "2.5 MT 4X4",
              "variant_display_name": "2.5 MT 4X4 [2011 - 2019]",
              "transportation_category": "Category_5",
              "transmission_type": "MT",
              "fuel_type": "Diesel",
              "status": "Active",
              "tax_value": "18",
              "ex_showroom_price": 2805000
            }
          ]
        }
      ]
    },
    {
      "year_id": 7055,
      "year": "2010",
      "models": [
        {
          "status": "Active",
          "model_id": 173,
          "make_id": 25,
          "model_name": "CEDIA",
          "model_display": "Cedia",
          "body_type": "Sedan",
          "is_popular": "no",
          "feed_img": "",
          "variants": [
            {
              "variant_id": 984,
              "model_id": 173,
              "variant_name": "NEW SPORTS",
              "variant_name_short": "NEW SPORTS",
              "variant_display_name": "NEW SPORTS",
              "transportation_category": "Category_3",
              "transmission_type": "MT",
              "fuel_type": "Petrol",
              "status": "Active",
              "tax_value": "18",
              "ex_showroom_price": null
            },
            {
              "variant_id": 2166,
              "model_id": 173,
              "variant_name": "SPORTS",
              "variant_name_short": "SPORTS",
              "variant_display_name": "SPORTS",
              "transportation_category": "Category_3",
              "transmission_type": "MT",
              "fuel_type": "Petrol",
              "status": "Active",
              "tax_value": "18",
              "ex_showroom_price": 990000
            }
          ]
        },
        {
          "status": "Active",
          "model_id": 174,
          "make_id": 25,
          "model_name": "LANCER",
          "model_display": "Lancer",
          "body_type": "Sedan",
          "is_popular": "yes",
          "feed_img": "",
          "variants": [
            {
              "variant_id": 985,
              "model_id": 174,
              "variant_name": "LXD 2.0",
              "variant_name_short": "LXD 2.0",
              "variant_display_name": "LXD 2.0",
              "transportation_category": "Category_4",
              "transmission_type": "MT",
              "fuel_type": "Diesel",
              "status": "Active",
              "tax_value": "18",
              "ex_showroom_price": null
            },
            {
              "variant_id": 2070,
              "model_id": 174,
              "variant_name": "LXI 1.5",
              "variant_name_short": "LXI 1.5",
              "variant_display_name": "LXI 1.5",
              "transportation_category": "Category_4",
              "transmission_type": "MT",
              "fuel_type": "Petrol",
              "status": "Active",
              "tax_value": "18",
              "ex_showroom_price": null
            }
          ]
        },
        {
          "status": "Active",
          "model_id": 176,
          "make_id": 25,
          "model_name": "MONTERO",
          "model_display": "Montero",
          "body_type": "Luxury SUV",
          "is_popular": "no",
          "feed_img": "1",
          "variants": [
            {
              "variant_id": 987,
              "model_id": 176,
              "variant_name": "DI D AT",
              "variant_name_short": "DI D AT",
              "variant_display_name": "DI D AT",
              "transportation_category": "Category_5",
              "transmission_type": "AT",
              "fuel_type": "Diesel",
              "status": "Active",
              "tax_value": "18",
              "ex_showroom_price": null
            },
            {
              "variant_id": 988,
              "model_id": 176,
              "variant_name": "DI D MT",
              "variant_name_short": "DI D MT",
              "variant_display_name": "DI D MT",
              "transportation_category": "Category_5",
              "transmission_type": "MT",
              "fuel_type": "Diesel",
              "status": "Active",
              "tax_value": "18",
              "ex_showroom_price": null
            }
          ]
        },
        {
          "status": "Active",
          "model_id": 177,
          "make_id": 25,
          "model_name": "OUTLANDER",
          "model_display": "Outlander",
          "body_type": "Luxury SUV",
          "is_popular": "yes",
          "feed_img": "1",
          "variants": [
            {
              "variant_id": 989,
              "model_id": 177,
              "variant_name": "2.4 MIVEC",
              "variant_name_short": "2.4 MIVEC",
              "variant_display_name": "2.4 MIVEC [2008 - 2013]",
              "transportation_category": "Category_5",
              "transmission_type": "MT",
              "fuel_type": "Petrol",
              "status": "Active",
              "tax_value": "18",
              "ex_showroom_price": 2048000
            }
          ]
        },
        {
          "status": "Active",
          "model_id": 178,
          "make_id": 25,
          "model_name": "PAJERO",
          "model_display": "Pajero",
          "body_type": "Luxury SUV",
          "is_popular": "yes",
          "feed_img": "1",
          "variants": [
            {
              "variant_id": 6113,
              "model_id": 178,
              "variant_name": "SFX 2.8 4*4 MT",
              "variant_name_short": "SFX 2.8 4*4 MT",
              "variant_display_name": "SFX 2.8 4*4 MT [1985 - 2010]",
              "transportation_category": "Category_5",
              "transmission_type": "MT",
              "fuel_type": "Diesel",
              "status": "Active",
              "tax_value": "18",
              "ex_showroom_price": 750000
            },
            {
              "variant_id": 990,
              "model_id": 178,
              "variant_name": "SFX 2.8",
              "variant_name_short": "SFX 2.8",
              "variant_display_name": "SFX 2.8 [1985 - 2010]",
              "transportation_category": "Category_5",
              "transmission_type": "MT",
              "fuel_type": "Diesel",
              "status": "Active",
              "tax_value": "18",
              "ex_showroom_price": 750000
            },
            {
              "variant_id": 4974,
              "model_id": 178,
              "variant_name": "SFX 2.8 AT 4X4",
              "variant_name_short": "SFX 2.8 AT 4X4",
              "variant_display_name": "SFX 2.8 AT 4X4 [1985 - 2010]",
              "transportation_category": "Category_5",
              "transmission_type": "AT",
              "fuel_type": "Diesel",
              "status": "Active",
              "tax_value": "18",
              "ex_showroom_price": 749999
            }
          ]
        },
        {
          "status": "Active",
          "model_id": 179,
          "make_id": 25,
          "model_name": "PAJERO SPORT",
          "model_display": "Pajero Sport",
          "body_type": "Luxury SUV",
          "is_popular": "yes",
          "feed_img": "1",
          "variants": [
            {
              "variant_id": 991,
              "model_id": 179,
              "variant_name": "2.5 MT",
              "variant_name_short": "2.5 MT",
              "variant_display_name": "2.5 MT",
              "transportation_category": "Category_5",
              "transmission_type": "MT",
              "fuel_type": "Diesel",
              "status": "Active",
              "tax_value": "18",
              "ex_showroom_price": null
            }
          ]
        }
      ]
    },
    {
      "year_id": 7926,
      "year": "2009",
      "models": [
        {
          "status": "Active",
          "model_id": 173,
          "make_id": 25,
          "model_name": "CEDIA",
          "model_display": "Cedia",
          "body_type": "Sedan",
          "is_popular": "no",
          "feed_img": ""
        },
        {
          "status": "Active",
          "model_id": 174,
          "make_id": 25,
          "model_name": "LANCER",
          "model_display": "Lancer",
          "body_type": "Sedan",
          "is_popular": "yes",
          "feed_img": ""
        },
        {
          "status": "Active",
          "model_id": 176,
          "make_id": 25,
          "model_name": "MONTERO",
          "model_display": "Montero",
          "body_type": "Luxury SUV",
          "is_popular": "no",
          "feed_img": "1"
        },
        {
          "status": "Active",
          "model_id": 177,
          "make_id": 25,
          "model_name": "OUTLANDER",
          "model_display": "Outlander",
          "body_type": "Luxury SUV",
          "is_popular": "yes",
          "feed_img": "1"
        },
        {
          "status": "Active",
          "model_id": 178,
          "make_id": 25,
          "model_name": "PAJERO",
          "model_display": "Pajero",
          "body_type": "Luxury SUV",
          "is_popular": "yes",
          "feed_img": "1"
        },
        {
          "status": "Active",
          "model_id": 179,
          "make_id": 25,
          "model_name": "PAJERO SPORT",
          "model_display": "Pajero Sport",
          "body_type": "Luxury SUV",
          "is_popular": "yes",
          "feed_img": "1"
        }
      ]
    },
    {
      "year_id": 8567,
      "year": "2008",
      "models": [
        {
          "status": "Active",
          "model_id": 173,
          "make_id": 25,
          "model_name": "CEDIA",
          "model_display": "Cedia",
          "body_type": "Sedan",
          "is_popular": "no",
          "feed_img": ""
        },
        {
          "status": "Active",
          "model_id": 174,
          "make_id": 25,
          "model_name": "LANCER",
          "model_display": "Lancer",
          "body_type": "Sedan",
          "is_popular": "yes",
          "feed_img": ""
        },
        {
          "status": "Active",
          "model_id": 176,
          "make_id": 25,
          "model_name": "MONTERO",
          "model_display": "Montero",
          "body_type": "Luxury SUV",
          "is_popular": "no",
          "feed_img": "1"
        },
        {
          "status": "Active",
          "model_id": 177,
          "make_id": 25,
          "model_name": "OUTLANDER",
          "model_display": "Outlander",
          "body_type": "Luxury SUV",
          "is_popular": "yes",
          "feed_img": "1"
        },
        {
          "status": "Active",
          "model_id": 178,
          "make_id": 25,
          "model_name": "PAJERO",
          "model_display": "Pajero",
          "body_type": "Luxury SUV",
          "is_popular": "yes",
          "feed_img": "1"
        },
        {
          "status": "Active",
          "model_id": 179,
          "make_id": 25,
          "model_name": "PAJERO SPORT",
          "model_display": "Pajero Sport",
          "body_type": "Luxury SUV",
          "is_popular": "yes",
          "feed_img": "1"
        }
      ]
    },
    {
      "year_id": 9090,
      "year": "2007",
      "models": [
        {
          "status": "Active",
          "model_id": 173,
          "make_id": 25,
          "model_name": "CEDIA",
          "model_display": "Cedia",
          "body_type": "Sedan",
          "is_popular": "no",
          "feed_img": ""
        },
        {
          "status": "Active",
          "model_id": 174,
          "make_id": 25,
          "model_name": "LANCER",
          "model_display": "Lancer",
          "body_type": "Sedan",
          "is_popular": "yes",
          "feed_img": ""
        },
        {
          "status": "Active",
          "model_id": 176,
          "make_id": 25,
          "model_name": "MONTERO",
          "model_display": "Montero",
          "body_type": "Luxury SUV",
          "is_popular": "no",
          "feed_img": "1"
        },
        {
          "status": "Active",
          "model_id": 178,
          "make_id": 25,
          "model_name": "PAJERO",
          "model_display": "Pajero",
          "body_type": "Luxury SUV",
          "is_popular": "yes",
          "feed_img": "1"
        }
      ]
    },
    {
      "year_id": 9557,
      "year": "2006",
      "models": [
        {
          "status": "Active",
          "model_id": 173,
          "make_id": 25,
          "model_name": "CEDIA",
          "model_display": "Cedia",
          "body_type": "Sedan",
          "is_popular": "no",
          "feed_img": ""
        },
        {
          "status": "Active",
          "model_id": 174,
          "make_id": 25,
          "model_name": "LANCER",
          "model_display": "Lancer",
          "body_type": "Sedan",
          "is_popular": "yes",
          "feed_img": ""
        },
        {
          "status": "Active",
          "model_id": 176,
          "make_id": 25,
          "model_name": "MONTERO",
          "model_display": "Montero",
          "body_type": "Luxury SUV",
          "is_popular": "no",
          "feed_img": "1"
        },
        {
          "status": "Active",
          "model_id": 178,
          "make_id": 25,
          "model_name": "PAJERO",
          "model_display": "Pajero",
          "body_type": "Luxury SUV",
          "is_popular": "yes",
          "feed_img": "1"
        }
      ]
    },
    {
      "year_id": 54474,
      "year": "2005",
      "models": [
        {
          "status": "Active",
          "model_id": 173,
          "make_id": 25,
          "model_name": "CEDIA",
          "model_display": "Cedia",
          "body_type": "Sedan",
          "is_popular": "no",
          "feed_img": ""
        },
        {
          "status": "Active",
          "model_id": 174,
          "make_id": 25,
          "model_name": "LANCER",
          "model_display": "Lancer",
          "body_type": "Sedan",
          "is_popular": "yes",
          "feed_img": ""
        },
        {
          "status": "Active",
          "model_id": 178,
          "make_id": 25,
          "model_name": "PAJERO",
          "model_display": "Pajero",
          "body_type": "Luxury SUV",
          "is_popular": "yes",
          "feed_img": "1"
        }
      ]
    },
    {
      "year_id": 54473,
      "year": "2004",
      "models": [
        {
          "status": "Active",
          "model_id": 173,
          "make_id": 25,
          "model_name": "CEDIA",
          "model_display": "Cedia",
          "body_type": "Sedan",
          "is_popular": "no",
          "feed_img": ""
        },
        {
          "status": "Active",
          "model_id": 174,
          "make_id": 25,
          "model_name": "LANCER",
          "model_display": "Lancer",
          "body_type": "Sedan",
          "is_popular": "yes",
          "feed_img": ""
        },
        {
          "status": "Active",
          "model_id": 178,
          "make_id": 25,
          "model_name": "PAJERO",
          "model_display": "Pajero",
          "body_type": "Luxury SUV",
          "is_popular": "yes",
          "feed_img": "1"
        }
      ]
    },
    {
      "year_id": 27862,
      "year": "2003",
      "models": [
        {
          "status": "Active",
          "model_id": 173,
          "make_id": 25,
          "model_name": "CEDIA",
          "model_display": "Cedia",
          "body_type": "Sedan",
          "is_popular": "no",
          "feed_img": ""
        },
        {
          "status": "Active",
          "model_id": 174,
          "make_id": 25,
          "model_name": "LANCER",
          "model_display": "Lancer",
          "body_type": "Sedan",
          "is_popular": "yes",
          "feed_img": ""
        },
        {
          "status": "Active",
          "model_id": 178,
          "make_id": 25,
          "model_name": "PAJERO",
          "model_display": "Pajero",
          "body_type": "Luxury SUV",
          "is_popular": "yes",
          "feed_img": "1"
        }
      ]
    },
    {
      "year_id": 54471,
      "year": "2002",
      "models": [
        {
          "status": "Active",
          "model_id": 173,
          "make_id": 25,
          "model_name": "CEDIA",
          "model_display": "Cedia",
          "body_type": "Sedan",
          "is_popular": "no",
          "feed_img": ""
        },
        {
          "status": "Active",
          "model_id": 174,
          "make_id": 25,
          "model_name": "LANCER",
          "model_display": "Lancer",
          "body_type": "Sedan",
          "is_popular": "yes",
          "feed_img": ""
        },
        {
          "status": "Active",
          "model_id": 178,
          "make_id": 25,
          "model_name": "PAJERO",
          "model_display": "Pajero",
          "body_type": "Luxury SUV",
          "is_popular": "yes",
          "feed_img": "1"
        }
      ]
    },
    {
      "year_id": 54470,
      "year": "2001",
      "models": [
        {
          "status": "Active",
          "model_id": 173,
          "make_id": 25,
          "model_name": "CEDIA",
          "model_display": "Cedia",
          "body_type": "Sedan",
          "is_popular": "no",
          "feed_img": ""
        },
        {
          "status": "Active",
          "model_id": 174,
          "make_id": 25,
          "model_name": "LANCER",
          "model_display": "Lancer",
          "body_type": "Sedan",
          "is_popular": "yes",
          "feed_img": ""
        },
        {
          "status": "Active",
          "model_id": 178,
          "make_id": 25,
          "model_name": "PAJERO",
          "model_display": "Pajero",
          "body_type": "Luxury SUV",
          "is_popular": "yes",
          "feed_img": "1"
        }
      ]
    },
    {
      "year_id": 54469,
      "year": "2000",
      "models": [
        {
          "status": "Active",
          "model_id": 173,
          "make_id": 25,
          "model_name": "CEDIA",
          "model_display": "Cedia",
          "body_type": "Sedan",
          "is_popular": "no",
          "feed_img": ""
        },
        {
          "status": "Active",
          "model_id": 174,
          "make_id": 25,
          "model_name": "LANCER",
          "model_display": "Lancer",
          "body_type": "Sedan",
          "is_popular": "yes",
          "feed_img": ""
        },
        {
          "status": "Active",
          "model_id": 178,
          "make_id": 25,
          "model_name": "PAJERO",
          "model_display": "Pajero",
          "body_type": "Luxury SUV",
          "is_popular": "yes",
          "feed_img": "1"
        }
      ]
    },
    {
      "year_id": 54468,
      "year": "1999",
      "models": [
        {
          "status": "Active",
          "model_id": 173,
          "make_id": 25,
          "model_name": "CEDIA",
          "model_display": "Cedia",
          "body_type": "Sedan",
          "is_popular": "no",
          "feed_img": ""
        },
        {
          "status": "Active",
          "model_id": 174,
          "make_id": 25,
          "model_name": "LANCER",
          "model_display": "Lancer",
          "body_type": "Sedan",
          "is_popular": "yes",
          "feed_img": ""
        },
        {
          "status": "Active",
          "model_id": 178,
          "make_id": 25,
          "model_name": "PAJERO",
          "model_display": "Pajero",
          "body_type": "Luxury SUV",
          "is_popular": "yes",
          "feed_img": "1"
        }
      ]
    },
    {
      "year_id": 54467,
      "year": "1998",
      "models": [
        {
          "status": "Active",
          "model_id": 173,
          "make_id": 25,
          "model_name": "CEDIA",
          "model_display": "Cedia",
          "body_type": "Sedan",
          "is_popular": "no",
          "feed_img": ""
        },
        {
          "status": "Active",
          "model_id": 174,
          "make_id": 25,
          "model_name": "LANCER",
          "model_display": "Lancer",
          "body_type": "Sedan",
          "is_popular": "yes",
          "feed_img": ""
        },
        {
          "status": "Active",
          "model_id": 178,
          "make_id": 25,
          "model_name": "PAJERO",
          "model_display": "Pajero",
          "body_type": "Luxury SUV",
          "is_popular": "yes",
          "feed_img": "1"
        }
      ]
    },
    {
      "year_id": 54466,
      "year": "1997",
      "models": [
        {
          "status": "Active",
          "model_id": 173,
          "make_id": 25,
          "model_name": "CEDIA",
          "model_display": "Cedia",
          "body_type": "Sedan",
          "is_popular": "no",
          "feed_img": ""
        },
        {
          "status": "Active",
          "model_id": 503,
          "make_id": 25,
          "model_name": "FTO",
          "model_display": "FTO",
          "body_type": "Luxury Sedan",
          "is_popular": "no",
          "feed_img": "0"
        },
        {
          "status": "Active",
          "model_id": 178,
          "make_id": 25,
          "model_name": "PAJERO",
          "model_display": "Pajero",
          "body_type": "Luxury SUV",
          "is_popular": "yes",
          "feed_img": "1"
        }
      ]
    },
    {
      "year_id": 54465,
      "year": "1996",
      "models": [
        {
          "status": "Active",
          "model_id": 173,
          "make_id": 25,
          "model_name": "CEDIA",
          "model_display": "Cedia",
          "body_type": "Sedan",
          "is_popular": "no",
          "feed_img": ""
        },
        {
          "status": "Active",
          "model_id": 178,
          "make_id": 25,
          "model_name": "PAJERO",
          "model_display": "Pajero",
          "body_type": "Luxury SUV",
          "is_popular": "yes",
          "feed_img": "1"
        }
      ]
    },
    {
      "year_id": 23142,
      "year": "1995",
      "models": [
        {
          "status": "Active",
          "model_id": 173,
          "make_id": 25,
          "model_name": "CEDIA",
          "model_display": "Cedia",
          "body_type": "Sedan",
          "is_popular": "no",
          "feed_img": ""
        },
        {
          "status": "Active",
          "model_id": 174,
          "make_id": 25,
          "model_name": "LANCER",
          "model_display": "Lancer",
          "body_type": "Sedan",
          "is_popular": "yes",
          "feed_img": ""
        },
        {
          "status": "Active",
          "model_id": 178,
          "make_id": 25,
          "model_name": "PAJERO",
          "model_display": "Pajero",
          "body_type": "Luxury SUV",
          "is_popular": "yes",
          "feed_img": "1"
        }
      ]
    },
    {
      "year_id": 58564,
      "year": "1994",
      "models": [
        {
          "status": "Active",
          "model_id": 503,
          "make_id": 25,
          "model_name": "FTO",
          "model_display": "FTO",
          "body_type": "Luxury Sedan",
          "is_popular": "no",
          "feed_img": "0"
        },
        {
          "status": "Active",
          "model_id": 178,
          "make_id": 25,
          "model_name": "PAJERO",
          "model_display": "Pajero",
          "body_type": "Luxury SUV",
          "is_popular": "yes",
          "feed_img": "1"
        }
      ]
    },
    {
      "year_id": 58563,
      "year": "1993",
      "models": [
        {
          "status": "Active",
          "model_id": 178,
          "make_id": 25,
          "model_name": "PAJERO",
          "model_display": "Pajero",
          "body_type": "Luxury SUV",
          "is_popular": "yes",
          "feed_img": "1"
        }
      ]
    },
    {
      "year_id": 58562,
      "year": "1992",
      "models": [
        {
          "status": "Active",
          "model_id": 178,
          "make_id": 25,
          "model_name": "PAJERO",
          "model_display": "Pajero",
          "body_type": "Luxury SUV",
          "is_popular": "yes",
          "feed_img": "1"
        }
      ]
    },
    {
      "year_id": 58561,
      "year": "1991",
      "models": [
        {
          "status": "Active",
          "model_id": 178,
          "make_id": 25,
          "model_name": "PAJERO",
          "model_display": "Pajero",
          "body_type": "Luxury SUV",
          "is_popular": "yes",
          "feed_img": "1"
        }
      ]
    },
    {
      "year_id": 58560,
      "year": "1990",
      "models": [
        {
          "status": "Active",
          "model_id": 178,
          "make_id": 25,
          "model_name": "PAJERO",
          "model_display": "Pajero",
          "body_type": "Luxury SUV",
          "is_popular": "yes",
          "feed_img": "1"
        }
      ]
    },
    {
      "year_id": 58559,
      "year": "1989",
      "models": [
        {
          "status": "Active",
          "model_id": 178,
          "make_id": 25,
          "model_name": "PAJERO",
          "model_display": "Pajero",
          "body_type": "Luxury SUV",
          "is_popular": "yes",
          "feed_img": "1"
        }
      ]
    },
    {
      "year_id": 58558,
      "year": "1988",
      "models": [
        {
          "status": "Active",
          "model_id": 178,
          "make_id": 25,
          "model_name": "PAJERO",
          "model_display": "Pajero",
          "body_type": "Luxury SUV",
          "is_popular": "yes",
          "feed_img": "1"
        }
      ]
    },
    {
      "year_id": 58557,
      "year": "1987",
      "models": [
        {
          "status": "Active",
          "model_id": 178,
          "make_id": 25,
          "model_name": "PAJERO",
          "model_display": "Pajero",
          "body_type": "Luxury SUV",
          "is_popular": "yes",
          "feed_img": "1"
        }
      ]
    },
    {
      "year_id": 58556,
      "year": "1986",
      "models": [
        {
          "status": "Active",
          "model_id": 178,
          "make_id": 25,
          "model_name": "PAJERO",
          "model_display": "Pajero",
          "body_type": "Luxury SUV",
          "is_popular": "yes",
          "feed_img": "1"
        }
      ]
    },
    {
      "year_id": 58555,
      "year": "1985",
      "models": [
        {
          "status": "Active",
          "model_id": 178,
          "make_id": 25,
          "model_name": "PAJERO",
          "model_display": "Pajero",
          "body_type": "Luxury SUV",
          "is_popular": "yes",
          "feed_img": "1"
        }
      ]
    }
  ]
}